{
  "biography": "Eric Marlon Bishop (born December 13, 1967), known professionally as Jamie Foxx, is an American actor, singer, comedian, presenter, and producer. Foxx initially became known for his portrayal of Ray Charles in the 2004 biographical film Ray, for which he won the Academy Award, BAFTA, Screen Actors Guild Award, Critics' Choice Movie Award and Golden Globe Award for Best Actor. That same year, he was nominated for the Academy Award for Best Supporting Actor for his role in the crime film Collateral. Since spring 2017, Foxx has served as the host and executive producer of the Fox game show Beat Shazam.",
  "birthName": "Eric Marlon Bishop",
  "dateOfBirth": "Wed Dec 13 00:00:00 GMT 1967",
  "occupations": [
    ""
  ],
  "id": 42,
  "imageId": 61,
  "name": "Jamie Foxx",
  "rating": -1
}
